<?xml version="1.0" encoding="utf-8"?>
<!DOCTYPE hibernate-mapping PUBLIC "-//Hibernate/Hibernate Mapping DTD 3.0//EN"
"http://hibernate.sourceforge.net/hibernate-mapping-3.0.dtd">
<!-- 
    Mapping file autogenerated by MyEclipse Persistence Tools
-->
<hibernate-mapping>
    <class name="com.dhcc.ftp.entity.FtpProductMethodRel" table="FTP_PRODUCT_METHOD_REL" schema="FTP">
        <id name="productNo" type="java.lang.String">
            <column name="PRODUCT_NO" length="10" />
            <generator class="assigned" />
        </id>
        <property name="curNo" type="java.lang.String">
            <column name="CUR_NO" length="2" />
        </property>
        <property name="customerType" type="java.lang.String">
            <column name="CUSTOMER_TYPE" length="1" />
        </property>
        <property name="termType" type="java.lang.String">
            <column name="TERM_TYPE" length="30" />
        </property>
        <property name="rateType" type="java.lang.String">
            <column name="RATE_TYPE" length="1" />
        </property>
        <property name="amtType" type="java.lang.String">
            <column name="AMT_TYPE" length="1" />
        </property>
        <property name="businessName" type="java.lang.String">
            <column name="BUSINESS_NAME" />
        </property>
        <property name="businessNo" type="java.lang.String">
            <column name="BUSINESS_NO" length="10" />
        </property>
        <property name="productName" type="java.lang.String">
            <column name="PRODUCT_NAME" length="100" />
        </property>
        <property name="methodName" type="java.lang.String">
            <column name="METHOD_NAME" />
        </property>
        <property name="methodNo" type="java.lang.String">
            <column name="METHOD_NO" length="2" />
        </property>
        <property name="assignTerm" type="java.lang.Integer">
            <column name="ASSIGN_TERM" precision="6" scale="0" />
        </property>
        <property name="adjustRate" type="java.lang.Double">
            <column name="ADJUST_RATE" precision="8" scale="6" />
        </property>
        <property name="curveNo" type="java.lang.String">
            <column name="CURVE_NO" length="15" />
        </property>
        <property name="methodTypeNo" type="java.lang.String">
            <column name="METHOD_TYPE_NO" length="17" />
        </property>
        <property name="availableMethod" type="java.lang.String">
            <column name="AVAILABLE_METHOD" length="30" />
        </property>
        <property name="availableMethodNo" type="java.lang.String">
            <column name="AVAILABLE_METHOD_NO" length="2" />
        </property>
        <property name="appointRate" type="java.lang.Double">
            <column name="APPOINT_RATE" precision="8" scale="6" />
        </property>
        <property name="appointDeltaRate" type="java.lang.Double">
            <column name="APPOINT_DELTA_RATE" precision="8" scale="6" />
        </property>
        <property name="brNo" type="java.lang.String">
            <column name="BR_NO" length="10" />
        </property>
          <property name="lrAdjustRate" type="java.lang.Double">
            <column name="LR_ADJUST_RATE" precision="8" scale="6" />
        </property>
        <property name="epsAdjustRate" type="java.lang.Double">
            <column name="EPS_ADJUST_RATE" precision="8" scale="6" />
        </property>
        <property name="isTz" type="java.lang.String">
            <column name="is_tz" length="2" />
        </property>
    </class>
</hibernate-mapping>
